MANIFEST.in
setup.py
bcbio/__init__.py
bcbio/isatab/__init__.py
bcbio/isatab/parser.py
biopy_isatab.egg-info/PKG-INFO
biopy_isatab.egg-info/SOURCES.txt
biopy_isatab.egg-info/dependency_links.txt
biopy_isatab.egg-info/namespace_packages.txt
biopy_isatab.egg-info/top_level.txt
test/test_isatab.py
test/isatab/BII-I-1/a_metabolome.txt
test/isatab/BII-I-1/a_microarray.txt
test/isatab/BII-I-1/a_proteome.txt
test/isatab/BII-I-1/a_transcriptome.txt
test/isatab/BII-I-1/i_Investigation.txt
test/isatab/BII-I-1/s_BII-S-1.txt
test/isatab/BII-I-1/s_BII-S-2.txt
test/isatab/BII-S-3/a_gilbert-assay-Gx.txt
test/isatab/BII-S-3/a_gilbert-assay-Tx.txt
test/isatab/BII-S-3/i_gilbert.txt
test/isatab/BII-S-3/s_BII-S-3.txt
test/isatab/genelist/16862118-Figure2bSRAS.txt
test/isatab/genelist/a_set1.txt
test/isatab/genelist/i_Investigation.txt
test/isatab/genelist/s_NIH_GO_Project_1_Armstrong.txt
test/isatab/minimal/a_C2C12expr.txt
test/isatab/minimal/i_Investigation.txt
test/isatab/minimal/s_SB-S-E1.txt